mlops/__init__.py
mlops/dataset.py
mlops/local.py
mlops/s3.py
mlops/s3bigfile.py
mlops/s3querybigfile.py
mlops/s3querylight.py
mlops/s3selectbigfile.py
mlops/s3smartopen.py
mlops/s3stream.py
mlops/util.py
mlops/s3latency/__init__.py
mlops/s3latency/s3latency.py
mlops/s3query/__init__.py
mlops/s3query/s3query.py
mlops/s3query/setup.py
mlops/s3select/__init__.py
mlops/s3select/s3listthread.py
mlops/s3select/s3scanonekey.py
mlops/s3select/s3selecteventresult.py
mlops/s3select/setup.py
common_mlops-0.1.1.dist-info/LICENSE
common_mlops-0.1.1.dist-info/METADATA
common_mlops-0.1.1.dist-info/WHEEL
common_mlops-0.1.1.dist-info/top_level.txt
common_mlops-0.1.1.dist-info/RECORD
