Metadata-Version: 2.1
Name: common-mlops
Version: 0.1.1
Summary: Utilities of MLOps for INRIA
Home-page: https://gitlab.com/Inria-Chile/common-mlops
Author: Patricio Merino
Author-email: patricio.merino@inria.cl
License: MIT
Download-URL: https://gitlab.com/Inria-Chile/common-mlops/archive/v0.1.1.tar.gz
Platform: any
Classifier: Development Status :: 4 - Beta
Classifier: Intended Audience :: Developers
Classifier: License :: OSI Approved :: MIT License
Classifier: Natural Language :: English
Classifier: Operating System :: OS Independent
Classifier: Programming Language :: Python :: 3
Classifier: Topic :: Software Development :: Libraries :: Python Modules
Requires-Python: >=3.6
Requires-Dist: boto3 (>=1.16.61)
Requires-Dist: pandas (>=1.2.0)
Requires-Dist: gitdb2 (>=4.0.2)
Requires-Dist: dvc (>=2.0.1)
Requires-Dist: s3-streaming (>=0.0.3)
Requires-Dist: smart-open (>=4.2.0)
Requires-Dist: scikit-learn (>=0.24.1)
